rsstui/__init__.py
rsstui/app.py
rsstui/async_feed.py
rsstui/default_discover.json
rsstui/styles/app.tcss
rsstui-1.0.0.dist-info/licenses/LICENSE
rsstui-1.0.0.dist-info/METADATA
rsstui-1.0.0.dist-info/WHEEL
rsstui-1.0.0.dist-info/entry_points.txt
rsstui-1.0.0.dist-info/top_level.txt
rsstui-1.0.0.dist-info/RECORD
