Metadata-Version: 2.4
Name: rsstui
Version: 1.0.0
Summary: RSS reader TUI application built with Textual
Author: yehorscode
License-Expression: MIT
Project-URL: Homepage, https://github.com/yehorscode/RssTUI
Project-URL: Bug Reports, https://github.com/yehorscode/RssTUI/issues
Project-URL: Source, https://github.com/yehorscode/RssTUI
Keywords: rss,feed,reader,tui,terminal,textual,news
Classifier: Development Status :: 4 - Beta
Classifier: Intended Audience :: End Users/Desktop
Classifier: Operating System :: OS Independent
Classifier: Programming Language :: Python :: 3
Classifier: Programming Language :: Python :: 3.8
Classifier: Programming Language :: Python :: 3.9
Classifier: Programming Language :: Python :: 3.10
Classifier: Programming Language :: Python :: 3.11
Classifier: Programming Language :: Python :: 3.12
Classifier: Topic :: Internet :: WWW/HTTP :: Dynamic Content :: News/Diary
Classifier: Topic :: Terminals
Classifier: Environment :: Console :: Curses
Requires-Python: >=3.8
License-File: LICENSE
Requires-Dist: textual>=0.41.0
Requires-Dist: feedparser>=6.0.0
Requires-Dist: aiofiles>=23.0.0
Requires-Dist: aiohttp>=3.8.0
Requires-Dist: html2text>=2025.4.15
Provides-Extra: dev
Requires-Dist: textual-dev>=1.0.0; extra == "dev"
Dynamic: license-file
